src/__init__.py
src/aer_budget_analysis.py
src/aer_diag_cli.py
src/gen_budgets.py
src/gen_forcings.py
src/gen_spatial_distr.py
src/gen_vertical_distr.py
src/batch_script/__init__.py
src/scrip_utils/__init__.py
src/scrip_utils/gen_exodus.py
src/scrip_utils/gen_phys_grids.py
src/scrip_utils/gen_rll_grid.py
src/scrip_utils/gen_scrip_file.py
src/scrip_utils/get_face_area.py
src/utils/__init__.py
src/utils/aerdiag_plots.py
src/utils/asediag_utils.py
src/utils/html_utils.py
src/utils/nclCols.py
test/__init__.py
test/test_general.py
asediag-1.2.0.dist-info/AUTHORS.rst
asediag-1.2.0.dist-info/LICENSE
asediag-1.2.0.dist-info/METADATA
asediag-1.2.0.dist-info/WHEEL
asediag-1.2.0.dist-info/entry_points.txt
asediag-1.2.0.dist-info/top_level.txt
asediag-1.2.0.dist-info/RECORD
