Metadata-Version: 2.1
Name: asediag
Version: 1.2.0
Summary: Aerosol Diagnostics on Model Native Grid
Home-page: https://github.com/eagles-project/asediag
Author: Taufiq Hassan
Author-email: taufiq.hassan@pnnl.gov
Classifier: Programming Language :: Python :: 3
Classifier: License :: OSI Approved :: MIT License
Classifier: Operating System :: OS Independent
Requires-Python: >=3.9
License-File: LICENSE
License-File: AUTHORS.rst
Requires-Dist: cartopy
Requires-Dist: matplotlib
Requires-Dist: numpy
Requires-Dist: pandas
Requires-Dist: setuptools
Requires-Dist: xarray
Requires-Dist: six
